{"response": {"termsofService": "http://www.wunderground.com/weather/api/d/terms.html", "version": "0.1", "features": {"history": 1}}, "history": {"date": {"mday": "07", "hour": "12", "min": "00", "mon": "11", "pretty": "November 7, 2014", "year": "2014", "tzname": "America/Los_Angeles"}, "utcdate": {"mday": "07", "hour": "20", "min": "00", "mon": "11", "pretty": "November 7, 2014", "year": "2014", "tzname": "UTC"}, "observations": [{"heatindexm": "-9999", "windchillm": "-999", "wdire": "ESE", "wdird": "120", "windchilli": "-999", "hail": "0", "heatindexi": "-9999", "precipi": "-9999.00", "thunder": "0", "pressurei": "30.31", "snow": "0", "pressurem": "1026.3", "fog": "0", "icon": "clear", "precipm": "-9999.00", "conds": "Clear", "tornado": "0", "hum": "77", "tempi": "52.0", "tempm": "11.1", "dewptm": "7.2", "rain": "0", "dewpti": "45.0", "date": {"mday": "07", "hour": "00", "min": "53", "mon": "11", "pretty": "12:53 AM PST on November 07, 2014", "year": "2014", "tzname": "America/Los_Angeles"}, "visi": "10.0", "vism": "16.1", "utcdate": {"mday": "07", "hour": "08", "min": "53", "mon": "11", "pretty": "8:53 AM GMT on November 07, 2014", "year": "2014", "tzname": "UTC"}, "wgusti": "-9999.0", "metar": "METAR KBFI 070853Z 12003KT 10SM CLR 11/07 A3031 RMK AO2 SLP263 T01110072 51020", "wgustm": "-9999.0", "wspdi": "3.5", "wspdm": "5.6"}, {"heatindexm": "-9999", "windchillm": "-999", "wdire": "SSE", "wdird": "150", "windchilli": "-999", "hail": "0", "heatindexi": "-9999", "precipi": "-9999.00", "thunder": "0", "pressurei": "30.34", "snow": "0", "pressurem": "1027.2", "fog": "0", "icon": "partlycloudy", "precipm": "-9999.00", "conds": "Scattered Clouds", "tornado": "0", "hum": "80", "tempi": "51.1", "tempm": "10.6", "dewptm": "7.2", "rain": "0", "dewpti": "45.0", "date": {"mday": "07", "hour": "01", "min": "53", "mon": "11", "pretty": "1:53 AM PST on November 07, 2014", "year": "2014", "tzname": "America/Los_Angeles"}, "visi": "10.0", "vism": "16.1", "utcdate": {"mday": "07", "hour": "09", "min": "53", "mon": "11", "pretty": "9:53 AM GMT on November 07, 2014", "year": "2014", "tzname": "UTC"}, "wgusti": "-9999.0", "metar": "METAR KBFI 070953Z 15006KT 10SM SCT200 11/07 A3034 RMK AO2 SLP272 T01060072", "wgustm": "-9999.0", "wspdi": "6.9", "wspdm": "11.1"}, {"heatindexm": "-9999", "windchillm": "-999", "wdire": "ESE", "wdird": "120", "windchilli": "-999", "hail": "0", "heatindexi": "-9999", "precipi": "-9999.00", "thunder": "0", "pressurei": "30.36", "snow": "0", "pressurem": "1027.9", "fog": "0", "icon": "mostlycloudy", "precipm": "-9999.00", "conds": "Mostly Cloudy", "tornado": "0", "hum": "83", "tempi": "50.0", "tempm": "10.0", "dewptm": "7.2", "rain": "0", "dewpti": "45.0", "date": {"mday": "07", "hour": "02", "min": "53", "mon": "11", "pretty": "2:53 AM PST on November 07, 2014", "year": "2014", "tzname": "America/Los_Angeles"}, "visi": "10.0", "vism": "16.1", "utcdate": {"mday": "07", "hour": "10", "min": "53", "mon": "11", "pretty": "10:53 AM GMT on November 07, 2014", "year": "2014", "tzname": "UTC"}, "wgusti": "-9999.0", "metar": "METAR KBFI 071053Z 12004KT 10SM BKN050 10/07 A3036 RMK AO2 SLP279 T01000072", "wgustm": "-9999.0", "wspdi": "4.6", "wspdm": "7.4"}, {"heatindexm": "-9999", "windchillm": "-999", "wdire": "SE", "wdird": "130", "windchilli": "-999", "hail": "0", "heatindexi": "-9999", "precipi": "-9999.00", "thunder": "0", "pressurei": "30.37", "snow": "0", "pressurem": "1028.2", "fog": "0", "icon": "cloudy", "precipm": "-9999.00", "conds": "Overcast", "tornado": "0", "hum": "83", "tempi": "50.0", "tempm": "10.0", "dewptm": "7.2", "rain": "0", "dewpti": "45.0", "date": {"mday": "07", "hour": "03", "min": "53", "mon": "11", "pretty": "3:53 AM PST on November 07, 2014", "year": "2014", "tzname": "America/Los_Angeles"}, "visi": "10.0", "vism": "16.1", "utcdate": {"mday": "07", "hour": "11", "min": "53", "mon": "11", "pretty": "11:53 AM GMT on November 07, 2014", "year": "2014", "tzname": "UTC"}, "wgusti": "-9999.0", "metar": "METAR KBFI 071153Z 13006KT 10SM FEW040 OVC060 10/07 A3036 RMK AO2 SLP282 70019 T01000072 10133 20089 51018", "wgustm": "-9999.0", "wspdi": "6.9", "wspdm": "11.1"}, {"heatindexm": "-9999", "windchillm": "-999", "wdire": "SE", "wdird": "140", "windchilli": "-999", "hail": "0", "heatindexi": "-9999", "precipi": "-9999.00", "thunder": "0", "pressurei": "30.39", "snow": "0", "pressurem": "1028.9", "fog": "0", "icon": "cloudy", "precipm": "-9999.00", "conds": "Overcast", "tornado": "0", "hum": "83", "tempi": "50.0", "tempm": "10.0", "dewptm": "7.2", "rain": "0", "dewpti": "45.0", "date": {"mday": "07", "hour": "04", "min": "53", "mon": "11", "pretty": "4:53 AM PST on November 07, 2014", "year": "2014", "tzname": "America/Los_Angeles"}, "visi": "10.0", "vism": "16.1", "utcdate": {"mday": "07", "hour": "12", "min": "53", "mon": "11", "pretty": "12:53 PM GMT on November 07, 2014", "year": "2014", "tzname": "UTC"}, "wgusti": "-9999.0", "metar": "METAR KBFI 071253Z 14005KT 10SM OVC060 10/07 A3039 RMK AO2 SLP289 T01000072", "wgustm": "-9999.0", "wspdi": "5.8", "wspdm": "9.3"}, {"heatindexm": "-9999", "windchillm": "-999", "wdire": "SE", "wdird": "140", "windchilli": "-999", "hail": "0", "heatindexi": "-9999", "precipi": "-9999.00", "thunder": "0", "pressurei": "30.41", "snow": "0", "pressurem": "1029.8", "fog": "0", "icon": "cloudy", "precipm": "-9999.00", "conds": "Overcast", "tornado": "0", "hum": "83", "tempi": "48.9", "tempm": "9.4", "dewptm": "6.7", "rain": "0", "dewpti": "44.1", "date": {"mday": "07", "hour": "05", "min": "53", "mon": "11", "pretty": "5:53 AM PST on November 07, 2014", "year": "2014", "tzname": "America/Los_Angeles"}, "visi": "10.0", "vism": "16.1", "utcdate": {"mday": "07", "hour": "13", "min": "53", "mon": "11", "pretty": "1:53 PM GMT on November 07, 2014", "year": "2014", "tzname": "UTC"}, "wgusti": "-9999.0", "metar": "METAR KBFI 071353Z 14003KT 10SM OVC065 09/07 A3041 RMK AO2 SLP298 T00940067", "wgustm": "-9999.0", "wspdi": "3.5", "wspdm": "5.6"}, {"heatindexm": "-9999", "windchillm": "-999", "wdire": "SE", "wdird": "140", "windchilli": "-999", "hail": "0", "heatindexi": "-9999", "precipi": "-9999.00", "thunder": "0", "pressurei": "30.44", "snow": "0", "pressurem": "1030.6", "fog": "0", "icon": "mostlycloudy", "precipm": "-9999.00", "conds": "Mostly Cloudy", "tornado": "0", "hum": "86", "tempi": "48.0", "tempm": "8.9", "dewptm": "6.7", "rain": "0", "dewpti": "44.1", "date": {"mday": "07", "hour": "06", "min": "53", "mon": "11", "pretty": "6:53 AM PST on November 07, 2014", "year": "2014", "tzname": "America/Los_Angeles"}, "visi": "10.0", "vism": "16.1", "utcdate": {"mday": "07", "hour": "14", "min": "53", "mon": "11", "pretty": "2:53 PM GMT on November 07, 2014", "year": "2014", "tzname": "UTC"}, "wgusti": "-9999.0", "metar": "METAR KBFI 071453Z 14003KT 10SM BKN065 09/07 A3044 RMK AO2 SLP306 T00890067 53025", "wgustm": "-9999.0", "wspdi": "3.5", "wspdm": "5.6"}, {"heatindexm": "-9999", "windchillm": "-999", "wdire": "North", "wdird": "0", "windchilli": "-999", "hail": "0", "heatindexi": "-9999", "precipi": "-9999.00", "thunder": "0", "pressurei": "30.46", "snow": "0", "pressurem": "1031.5", "fog": "0", "icon": "clear", "precipm": "-9999.00", "conds": "Clear", "tornado": "0", "hum": "86", "tempi": "48.0", "tempm": "8.9", "dewptm": "6.7", "rain": "0", "dewpti": "44.1", "date": {"mday": "07", "hour": "07", "min": "53", "mon": "11", "pretty": "7:53 AM PST on November 07, 2014", "year": "2014", "tzname": "America/Los_Angeles"}, "visi": "10.0", "vism": "16.1", "utcdate": {"mday": "07", "hour": "15", "min": "53", "mon": "11", "pretty": "3:53 PM GMT on November 07, 2014", "year": "2014", "tzname": "UTC"}, "wgusti": "-9999.0", "metar": "METAR KBFI 071553Z 00000KT 10SM CLR 09/07 A3046 RMK AO2 SLP315 T00890067", "wgustm": "-9999.0", "wspdi": "0.0", "wspdm": "0.0"}, {"heatindexm": "-9999", "windchillm": "-999", "wdire": "SE", "wdird": "130", "windchilli": "-999", "hail": "0", "heatindexi": "-9999", "precipi": "-9999.00", "thunder": "0", "pressurei": "30.48", "snow": "0", "pressurem": "1032.0", "fog": "0", "icon": "partlycloudy", "precipm": "-9999.00", "conds": "Scattered Clouds", "tornado": "0", "hum": "80", "tempi": "51.1", "tempm": "10.6", "dewptm": "7.2", "rain": "0", "dewpti": "45.0", "date": {"mday": "07", "hour": "08", "min": "53", "mon": "11", "pretty": "8:53 AM PST on November 07, 2014", "year": "2014", "tzname": "America/Los_Angeles"}, "visi": "10.0", "vism": "16.1", "utcdate": {"mday": "07", "hour": "16", "min": "53", "mon": "11", "pretty": "4:53 PM GMT on November 07, 2014", "year": "2014", "tzname": "UTC"}, "wgusti": "-9999.0", "metar": "METAR KBFI 071653Z 13004KT 10SM SCT060 11/07 A3048 RMK AO2 SLP320 T01060072", "wgustm": "-9999.0", "wspdi": "4.6", "wspdm": "7.4"}, {"heatindexm": "-9999", "windchillm": "-999", "wdire": "North", "wdird": "0", "windchilli": "-999", "hail": "0", "heatindexi": "-9999", "precipi": "-9999.00", "thunder": "0", "pressurei": "30.48", "snow": "0", "pressurem": "1032.2", "fog": "0", "icon": "partlycloudy", "precipm": "-9999.00", "conds": "Scattered Clouds", "tornado": "0", "hum": "69", "tempi": "55.0", "tempm": "12.8", "dewptm": "7.2", "rain": "0", "dewpti": "45.0", "date": {"mday": "07", "hour": "09", "min": "53", "mon": "11", "pretty": "9:53 AM PST on November 07, 2014", "year": "2014", "tzname": "America/Los_Angeles"}, "visi": "10.0", "vism": "16.1", "utcdate": {"mday": "07", "hour": "17", "min": "53", "mon": "11", "pretty": "5:53 PM GMT on November 07, 2014", "year": "2014", "tzname": "UTC"}, "wgusti": "-9999.0", "metar": "METAR KBFI 071753Z COR 00000KT 10SM FEW020 SCT060 13/07 A3048 RMK AO2 SLP322 T01280072 10128 20089 51016", "wgustm": "-9999.0", "wspdi": "0.0", "wspdm": "0.0"}, {"heatindexm": "-9999", "windchillm": "-999", "wdire": "North", "wdird": "0", "windchilli": "-999", "hail": "0", "heatindexi": "-9999", "precipi": "-9999.00", "thunder": "0", "pressurei": "30.47", "snow": "0", "pressurem": "1031.8", "fog": "0", "icon": "mostlycloudy", "precipm": "-9999.00", "conds": "Mostly Cloudy", "tornado": "0", "hum": "58", "tempi": "57.9", "tempm": "14.4", "dewptm": "6.1", "rain": "0", "dewpti": "43.0", "date": {"mday": "07", "hour": "10", "min": "53", "mon": "11", "pretty": "10:53 AM PST on November 07, 2014", "year": "2014", "tzname": "America/Los_Angeles"}, "visi": "10.0", "vism": "16.1", "utcdate": {"mday": "07", "hour": "18", "min": "53", "mon": "11", "pretty": "6:53 PM GMT on November 07, 2014", "year": "2014", "tzname": "UTC"}, "wgusti": "-9999.0", "metar": "METAR KBFI 071853Z 00000KT 10SM FEW020 SCT038 BKN250 14/06 A3047 RMK AO2 SLP318 T01440061", "wgustm": "-9999.0", "wspdi": "0.0", "wspdm": "0.0"}, {"heatindexm": "-9999", "windchillm": "-999", "wdire": "North", "wdird": "0", "windchilli": "-999", "hail": "0", "heatindexi": "-9999", "precipi": "-9999.00", "thunder": "0", "pressurei": "30.48", "snow": "0", "pressurem": "1031.9", "fog": "0", "icon": "partlycloudy", "precipm": "-9999.00", "conds": "Scattered Clouds", "tornado": "0", "hum": "64", "tempi": "57.0", "tempm": "13.9", "dewptm": "7.2", "rain": "0", "dewpti": "45.0", "date": {"mday": "07", "hour": "11", "min": "53", "mon": "11", "pretty": "11:53 AM PST on November 07, 2014", "year": "2014", "tzname": "America/Los_Angeles"}, "visi": "10.0", "vism": "16.1", "utcdate": {"mday": "07", "hour": "19", "min": "53", "mon": "11", "pretty": "7:53 PM GMT on November 07, 2014", "year": "2014", "tzname": "UTC"}, "wgusti": "-9999.0", "metar": "METAR KBFI 071953Z 00000KT 10SM FEW015 SCT034 14/07 A3048 RMK AO2 SLP319 T01390072", "wgustm": "-9999.0", "wspdi": "0.0", "wspdm": "0.0"}, {"heatindexm": "-9999", "windchillm": "-999", "wdire": "WNW", "wdird": "300", "windchilli": "-999", "hail": "0", "heatindexi": "-9999", "precipi": "-9999.00", "thunder": "0", "pressurei": "30.45", "snow": "0", "pressurem": "1031.2", "fog": "0", "icon": "mostlycloudy", "precipm": "-9999.00", "conds": "Mostly Cloudy", "tornado": "0", "hum": "60", "tempi": "57.9", "tempm": "14.4", "dewptm": "6.7", "rain": "0", "dewpti": "44.1", "date": {"mday": "07", "hour": "12", "min": "53", "mon": "11", "pretty": "12:53 PM PST on November 07, 2014", "year": "2014", "tzname": "America/Los_Angeles"}, "visi": "10.0", "vism": "16.1", "utcdate": {"mday": "07", "hour": "20", "min": "53", "mon": "11", "pretty": "8:53 PM GMT on November 07, 2014", "year": "2014", "tzname": "UTC"}, "wgusti": "-9999.0", "metar": "METAR KBFI 072053Z 30004KT 10SM FEW025 BKN250 14/07 A3045 RMK AO2 SLP312 T01440067 58009", "wgustm": "-9999.0", "wspdi": "4.6", "wspdm": "7.4"}, {"heatindexm": "-9999", "windchillm": "-999", "wdire": "WNW", "wdird": "300", "windchilli": "-999", "hail": "0", "heatindexi": "-9999", "precipi": "-9999.00", "thunder": "0", "pressurei": "30.44", "snow": "0", "pressurem": "1030.6", "fog": "0", "icon": "partlycloudy", "precipm": "-9999.00", "conds": "Scattered Clouds", "tornado": "0", "hum": "58", "tempi": "59.0", "tempm": "15.0", "dewptm": "6.7", "rain": "0", "dewpti": "44.1", "date": {"mday": "07", "hour": "13", "min": "53", "mon": "11", "pretty": "1:53 PM PST on November 07, 2014", "year": "2014", "tzname": "America/Los_Angeles"}, "visi": "10.0", "vism": "16.1", "utcdate": {"mday": "07", "hour": "21", "min": "53", "mon": "11", "pretty": "9:53 PM GMT on November 07, 2014", "year": "2014", "tzname": "UTC"}, "wgusti": "-9999.0", "metar": "METAR KBFI 072153Z 30004KT 10SM FEW015 SCT030 15/07 A3044 RMK AO2 SLP306 T01500067", "wgustm": "-9999.0", "wspdi": "4.6", "wspdm": "7.4"}, {"heatindexm": "-9999", "windchillm": "-999", "wdire": "WNW", "wdird": "300", "windchilli": "-999", "hail": "0", "heatindexi": "-9999", "precipi": "-9999.00", "thunder": "0", "pressurei": "30.42", "snow": "0", "pressurem": "1030.1", "fog": "0", "icon": "partlycloudy", "precipm": "-9999.00", "conds": "Partly Cloudy", "tornado": "0", "hum": "55", "tempi": "59.0", "tempm": "15.0", "dewptm": "6.1", "rain": "0", "dewpti": "43.0", "date": {"mday": "07", "hour": "14", "min": "53", "mon": "11", "pretty": "2:53 PM PST on November 07, 2014", "year": "2014", "tzname": "America/Los_Angeles"}, "visi": "10.0", "vism": "16.1", "utcdate": {"mday": "07", "hour": "22", "min": "53", "mon": "11", "pretty": "10:53 PM GMT on November 07, 2014", "year": "2014", "tzname": "UTC"}, "wgusti": "-9999.0", "metar": "METAR KBFI 072253Z 30006KT 10SM FEW040 15/06 A3042 RMK AO2 SLP301 T01500061", "wgustm": "-9999.0", "wspdi": "6.9", "wspdm": "11.1"}, {"heatindexm": "-9999", "windchillm": "-999", "wdire": "NW", "wdird": "310", "windchilli": "-999", "hail": "0", "heatindexi": "-9999", "precipi": "-9999.00", "thunder": "0", "pressurei": "30.42", "snow": "0", "pressurem": "1029.9", "fog": "0", "icon": "clear", "precipm": "-9999.00", "conds": "Clear", "tornado": "0", "hum": "53", "tempi": "57.9", "tempm": "14.4", "dewptm": "5.0", "rain": "0", "dewpti": "41.0", "date": {"mday": "07", "hour": "15", "min": "53", "mon": "11", "pretty": "3:53 PM PST on November 07, 2014", "year": "2014", "tzname": "America/Los_Angeles"}, "visi": "10.0", "vism": "16.1", "utcdate": {"mday": "07", "hour": "23", "min": "53", "mon": "11", "pretty": "11:53 PM GMT on November 07, 2014", "year": "2014", "tzname": "UTC"}, "wgusti": "-9999.0", "metar": "METAR KBFI 072353Z 31004KT 10SM CLR 14/05 A3042 RMK AO2 SLP299 T01440050 10150 20128 56014", "wgustm": "-9999.0", "wspdi": "4.6", "wspdm": "7.4"}, {"heatindexm": "-9999", "windchillm": "-999", "wdire": "Variable", "wdird": "0", "windchilli": "-999", "hail": "0", "heatindexi": "-9999", "precipi": "-9999.00", "thunder": "0", "pressurei": "30.42", "snow": "0", "pressurem": "1030.0", "fog": "0", "icon": "partlycloudy", "precipm": "-9999.00", "conds": "Scattered Clouds", "tornado": "0", "hum": "53", "tempi": "57.0", "tempm": "13.9", "dewptm": "4.4", "rain": "0", "dewpti": "39.9", "date": {"mday": "07", "hour": "16", "min": "53", "mon": "11", "pretty": "4:53 PM PST on November 07, 2014", "year": "2014", "tzname": "America/Los_Angeles"}, "visi": "10.0", "vism": "16.1", "utcdate": {"mday": "08", "hour": "00", "min": "53", "mon": "11", "pretty": "12:53 AM GMT on November 08, 2014", "year": "2014", "tzname": "UTC"}, "wgusti": "-9999.0", "metar": "METAR KBFI 080053Z VRB03KT 10SM FEW040 SCT250 14/04 A3042 RMK AO2 SLP300 T01390044", "wgustm": "-9999.0", "wspdi": "3.5", "wspdm": "5.6"}, {"heatindexm": "-9999", "windchillm": "-999", "wdire": "NNW", "wdird": "340", "windchilli": "-999", "hail": "0", "heatindexi": "-9999", "precipi": "-9999.00", "thunder": "0", "pressurei": "30.42", "snow": "0", "pressurem": "1030.0", "fog": "0", "icon": "clear", "precipm": "-9999.00", "conds": "Clear", "tornado": "0", "hum": "62", "tempi": "55.0", "tempm": "12.8", "dewptm": "5.6", "rain": "0", "dewpti": "42.1", "date": {"mday": "07", "hour": "17", "min": "53", "mon": "11", "pretty": "5:53 PM PST on November 07, 2014", "year": "2014", "tzname": "America/Los_Angeles"}, "visi": "10.0", "vism": "16.1", "utcdate": {"mday": "08", "hour": "01", "min": "53", "mon": "11", "pretty": "1:53 AM GMT on November 08, 2014", "year": "2014", "tzname": "UTC"}, "wgusti": "-9999.0", "metar": "METAR KBFI 080153Z 34003KT 10SM CLR 13/06 A3042 RMK AO2 SLP300 T01280056", "wgustm": "-9999.0", "wspdi": "3.5", "wspdm": "5.6"}, {"heatindexm": "-9999", "windchillm": "-999", "wdire": "North", "wdird": "0", "windchilli": "-999", "hail": "0", "heatindexi": "-9999", "precipi": "-9999.00", "thunder": "0", "pressurei": "30.40", "snow": "0", "pressurem": "1029.5", "fog": "0", "icon": "clear", "precipm": "-9999.00", "conds": "Clear", "tornado": "0", "hum": "66", "tempi": "53.1", "tempm": "11.7", "dewptm": "5.6", "rain": "0", "dewpti": "42.1", "date": {"mday": "07", "hour": "18", "min": "53", "mon": "11", "pretty": "6:53 PM PST on November 07, 2014", "year": "2014", "tzname": "America/Los_Angeles"}, "visi": "10.0", "vism": "16.1", "utcdate": {"mday": "08", "hour": "02", "min": "53", "mon": "11", "pretty": "2:53 AM GMT on November 08, 2014", "year": "2014", "tzname": "UTC"}, "wgusti": "-9999.0", "metar": "METAR KBFI 080253Z 00000KT 10SM CLR 12/06 A3040 RMK AO2 SLP295 T01170056 58004", "wgustm": "-9999.0", "wspdi": "0.0", "wspdm": "0.0"}, {"heatindexm": "-9999", "windchillm": "-999", "wdire": "North", "wdird": "0", "windchilli": "-999", "hail": "0", "heatindexi": "-9999", "precipi": "-9999.00", "thunder": "0", "pressurei": "30.39", "snow": "0", "pressurem": "1029.1", "fog": "0", "icon": "clear", "precipm": "-9999.00", "conds": "Clear", "tornado": "0", "hum": "74", "tempi": "51.1", "tempm": "10.6", "dewptm": "6.1", "rain": "0", "dewpti": "43.0", "date": {"mday": "07", "hour": "19", "min": "53", "mon": "11", "pretty": "7:53 PM PST on November 07, 2014", "year": "2014", "tzname": "America/Los_Angeles"}, "visi": "10.0", "vism": "16.1", "utcdate": {"mday": "08", "hour": "03", "min": "53", "mon": "11", "pretty": "3:53 AM GMT on November 08, 2014", "year": "2014", "tzname": "UTC"}, "wgusti": "-9999.0", "metar": "METAR KBFI 080353Z 00000KT 10SM CLR 11/06 A3039 RMK AO2 SLP291 T01060061", "wgustm": "-9999.0", "wspdi": "0.0", "wspdm": "0.0"}, {"heatindexm": "-9999", "windchillm": "-999", "wdire": "North", "wdird": "0", "windchilli": "-999", "hail": "0", "heatindexi": "-9999", "precipi": "-9999.00", "thunder": "0", "pressurei": "30.40", "snow": "0", "pressurem": "1029.2", "fog": "0", "icon": "clear", "precipm": "-9999.00", "conds": "Clear", "tornado": "0", "hum": "77", "tempi": "48.9", "tempm": "9.4", "dewptm": "5.6", "rain": "0", "dewpti": "42.1", "date": {"mday": "07", "hour": "20", "min": "53", "mon": "11", "pretty": "8:53 PM PST on November 07, 2014", "year": "2014", "tzname": "America/Los_Angeles"}, "visi": "10.0", "vism": "16.1", "utcdate": {"mday": "08", "hour": "04", "min": "53", "mon": "11", "pretty": "4:53 AM GMT on November 08, 2014", "year": "2014", "tzname": "UTC"}, "wgusti": "-9999.0", "metar": "METAR KBFI 080453Z 00000KT 10SM CLR 09/06 A3040 RMK AO2 SLP292 T00940056", "wgustm": "-9999.0", "wspdi": "0.0", "wspdm": "0.0"}, {"heatindexm": "-9999", "windchillm": "-999", "wdire": "North", "wdird": "0", "windchilli": "-999", "hail": "0", "heatindexi": "-9999", "precipi": "-9999.00", "thunder": "0", "pressurei": "30.40", "snow": "0", "pressurem": "1029.3", "fog": "0", "icon": "clear", "precipm": "-9999.00", "conds": "Clear", "tornado": "0", "hum": "77", "tempi": "48.9", "tempm": "9.4", "dewptm": "5.6", "rain": "0", "dewpti": "42.1", "date": {"mday": "07", "hour": "21", "min": "53", "mon": "11", "pretty": "9:53 PM PST on November 07, 2014", "year": "2014", "tzname": "America/Los_Angeles"}, "visi": "10.0", "vism": "16.1", "utcdate": {"mday": "08", "hour": "05", "min": "53", "mon": "11", "pretty": "5:53 AM GMT on November 08, 2014", "year": "2014", "tzname": "UTC"}, "wgusti": "-9999.0", "metar": "METAR KBFI 080553Z 00000KT 10SM CLR 09/06 A3040 RMK AO2 SLP293 T00940056 10144 20089 55002", "wgustm": "-9999.0", "wspdi": "0.0", "wspdm": "0.0"}, {"heatindexm": "-9999", "windchillm": "-999", "wdire": "North", "wdird": "0", "windchilli": "-999", "hail": "0", "heatindexi": "-9999", "precipi": "-9999.00", "thunder": "0", "pressurei": "30.40", "snow": "0", "pressurem": "1029.3", "fog": "0", "icon": "clear", "precipm": "-9999.00", "conds": "Clear", "tornado": "0", "hum": "80", "tempi": "46.9", "tempm": "8.3", "dewptm": "5.0", "rain": "0", "dewpti": "41.0", "date": {"mday": "07", "hour": "22", "min": "53", "mon": "11", "pretty": "10:53 PM PST on November 07, 2014", "year": "2014", "tzname": "America/Los_Angeles"}, "visi": "10.0", "vism": "16.1", "utcdate": {"mday": "08", "hour": "06", "min": "53", "mon": "11", "pretty": "6:53 AM GMT on November 08, 2014", "year": "2014", "tzname": "UTC"}, "wgusti": "-9999.0", "metar": "METAR KBFI 080653Z 00000KT 10SM CLR 08/05 A3040 RMK AO2 SLP293 T00830050", "wgustm": "-9999.0", "wspdi": "0.0", "wspdm": "0.0"}, {"heatindexm": "-9999", "windchillm": "-999", "wdire": "North", "wdird": "0", "windchilli": "-999", "hail": "0", "heatindexi": "-9999", "precipi": "-9999.00", "thunder": "0", "pressurei": "30.39", "snow": "0", "pressurem": "1029.1", "fog": "0", "icon": "clear", "precipm": "-9999.00", "conds": "Clear", "tornado": "0", "hum": "82", "tempi": "45.0", "tempm": "7.2", "dewptm": "4.4", "rain": "0", "dewpti": "39.9", "date": {"mday": "07", "hour": "23", "min": "53", "mon": "11", "pretty": "11:53 PM PST on November 07, 2014", "year": "2014", "tzname": "America/Los_Angeles"}, "visi": "10.0", "vism": "16.1", "utcdate": {"mday": "08", "hour": "07", "min": "53", "mon": "11", "pretty": "7:53 AM GMT on November 08, 2014", "year": "2014", "tzname": "UTC"}, "wgusti": "-9999.0", "metar": "METAR KBFI 080753Z 00000KT 10SM CLR 07/04 A3039 RMK AO2 SLP291 T00720044 401500072", "wgustm": "-9999.0", "wspdi": "0.0", "wspdm": "0.0"}], "dailysummary": [{"maxpressurem": "1032", "maxdewptm": "7", "maxpressurei": "30.48", "maxdewpti": "45", "since1julheatingdegreedaysnormal": "", "heatingdegreedaysnormal": "", "since1sepcoolingdegreedaysnormal": "", "hail": "0", "since1julsnowfallm": "", "date": {"mday": "07", "hour": "12", "min": "00", "mon": "11", "pretty": "12:00 PM PST on November 07, 2014", "year": "2014", "tzname": "America/Los_Angeles"}, "since1julheatingdegreedays": "", "maxvisi": "10", "since1sepheatingdegreedaysnormal": "", "heatingdegreedays": "12", "mindewptm": "4", "since1sepheatingdegreedays": "", "maxwspdm": "11", "since1julsnowfalli": "", "since1sepcoolingdegreedays": "", "snow": "0", "meanvism": "16", "meandewptm": "6", "snowdepthm": "", "meanvisi": "10", "fog": "0", "snowdepthi": "", "minvism": "16", "since1jancoolingdegreedays": "", "minvisi": "10", "coolingdegreedaysnormal": "", "gdegreedays": "2", "maxwspdi": "7", "meanwindspdi": "3", "meanpressurei": "30.41", "monthtodateheatingdegreedaysnormal": "", "meanwindspdm": "5", "meanpressurem": "1030", "tornado": "0", "mindewpti": "40", "mintempi": "45", "meandewpti": "43", "rain": "0", "mintempm": "7", "minhumidity": "53", "precipsource": "", "minwspdi": "0", "meanwdird": "140", "meanwdire": "", "minwspdm": "0", "monthtodatesnowfalli": "", "monthtodatecoolingdegreedaysnormal": "", "monthtodatesnowfallm": "", "maxhumidity": "86", "coolingdegreedays": "0", "maxtempm": "15", "minpressurei": "30.31", "monthtodatecoolingdegreedays": "", "maxtempi": "59", "minpressurem": "1026", "humidity": "", "precipi": "0.00", "snowfalli": "0.00", "since1jancoolingdegreedaysnormal": "", "precipm": "0.00", "snowfallm": "0.00", "thunder": "0", "monthtodateheatingdegreedays": "", "meantempi": "52", "maxvism": "16", "meantempm": "11"}]}}